simplicialx/__init__.py
simplicialx/_validation.py
simplicialx/scaffold.py
simplicialx/simplicial.py
simplicialx-0.1.0.dist-info/METADATA
simplicialx-0.1.0.dist-info/WHEEL
simplicialx-0.1.0.dist-info/top_level.txt
simplicialx-0.1.0.dist-info/RECORD
