Metadata-Version: 2.4
Name: simplicialx
Version: 0.1.0
Author: Alexander Serebrennikov, Oleg Kachan
License-Expression: GPL-2.0-only
Requires-Dist: numpy
Requires-Dist: networkx
Requires-Dist: sympy
